{
    "uuid": [
        {
            "value": "266579dc-d316-4755-8fea-d7b0819af81b"
        }
    ],
    "langcode": [
        {
            "value": "en"
        }
    ],
    "uid": [
        {
            "target_type": "user",
            "target_uuid": "e5c3b379-0dd0-4c71-8b8b-1cf235008711"
        }
    ],
    "filename": [
        {
            "value": "generateImage_LOmBHm.jpg"
        }
    ],
    "uri": [
        {
            "value": "public:\/\/2023-01\/generateImage_LOmBHm.jpg"
        }
    ],
    "filemime": [
        {
            "value": "image\/jpeg"
        }
    ],
    "filesize": [
        {
            "value": 3892
        }
    ],
    "status": [
        {
            "value": true
        }
    ],
    "created": [
        {
            "value": "2023-01-07T11:12:55+00:00",
            "format": "Y-m-d\\TH:i:sP"
        }
    ],
    "changed": [
        {
            "value": "2023-01-07T11:12:55+00:00",
            "format": "Y-m-d\\TH:i:sP"
        }
    ]
}