{
    "uuid": [
        {
            "value": "5f10509b-0f3d-4c9c-a5b8-842ba96455e5"
        }
    ],
    "langcode": [
        {
            "value": "en"
        }
    ],
    "uid": [
        {
            "target_type": "user",
            "target_uuid": "e5c3b379-0dd0-4c71-8b8b-1cf235008711"
        }
    ],
    "filename": [
        {
            "value": "generateImage_rga8L9.jpg"
        }
    ],
    "uri": [
        {
            "value": "public:\/\/2023-01\/generateImage_rga8L9.jpg"
        }
    ],
    "filemime": [
        {
            "value": "image\/jpeg"
        }
    ],
    "filesize": [
        {
            "value": 9432
        }
    ],
    "status": [
        {
            "value": true
        }
    ],
    "created": [
        {
            "value": "2023-01-07T10:30:08+00:00",
            "format": "Y-m-d\\TH:i:sP"
        }
    ],
    "changed": [
        {
            "value": "2023-01-07T10:30:08+00:00",
            "format": "Y-m-d\\TH:i:sP"
        }
    ]
}