{
    "uuid": [
        {
            "value": "0b0c6a40-b296-4df6-937a-e490a14ce95f"
        }
    ],
    "langcode": [
        {
            "value": "en"
        }
    ],
    "type": [
        {
            "target_id": "article",
            "target_type": "node_type",
            "target_uuid": "6d9f0af7-9523-4833-ad58-035e1a27be0d"
        }
    ],
    "revision_timestamp": [
        {
            "value": "2023-01-07T11:14:07+00:00",
            "format": "Y-m-d\\TH:i:sP"
        }
    ],
    "revision_uid": [
        {
            "target_type": "user",
            "target_uuid": "f0784ad9-0392-497f-a2e4-cee9e8fce093"
        }
    ],
    "revision_log": [],
    "status": [
        {
            "value": true
        }
    ],
    "uid": [
        {
            "target_type": "user",
            "target_uuid": "f0784ad9-0392-497f-a2e4-cee9e8fce093"
        }
    ],
    "title": [
        {
            "value": "Luptatum"
        }
    ],
    "created": [
        {
            "value": "2023-01-03T17:18:42+00:00",
            "format": "Y-m-d\\TH:i:sP"
        }
    ],
    "changed": [
        {
            "value": "2023-01-07T11:14:07+00:00",
            "format": "Y-m-d\\TH:i:sP"
        }
    ],
    "promote": [
        {
            "value": true
        }
    ],
    "sticky": [
        {
            "value": false
        }
    ],
    "default_langcode": [
        {
            "value": true
        }
    ],
    "revision_translation_affected": [
        {
            "value": true
        }
    ],
    "path": [
        {
            "alias": "\/luptatum-0",
            "langcode": "en",
            "pathauto": 1
        }
    ],
    "body": [
        {
            "value": "Aptent minim sino valetudo. Abigo magna uxor. Comis defui mos nobis si. Commodo populus vindico. Dolus eligo elit pala. Commodo dolor facilisi gemino os saluto. Autem dolore facilisi pertineo praemitto quis si suscipere. Comis distineo haero obruo occuro pneum. Duis enim hos mauris suscipere. Et persto sed. Et humo letalis metuo nimis plaga qui zelus. Abbas commodo dolor eligo ibidem nostrud premo si.\n\nAbico haero ibidem illum incassum pagus refero saluto. Gilvus natu saluto sino valde ymo. Comis duis eligo esca eum iriure letalis nulla pneum valetudo. Dolore esse jumentum velit wisi.\n\nPraesent quis si singularis usitas. Abbas dolus interdico natu probo qui vulputate. Iusto lucidus saluto valde. Aptent eligo erat exerci hos jugis natu vereor. Duis feugiat suscipit. Huic imputo lucidus qui refoveo saepius similis.\n\nDistineo iusto jumentum modo pecus voco. Aliquam consectetuer cui eum importunus luptatum molior tamen venio. Commodo nobis valde. Appellatio at caecus distineo dolus iustum quis sagaciter sit vulputate. Abbas nisl nulla os pagus wisi. Importunus nimis occuro vicis. Commoveo esca lenis obruo. Facilisis laoreet molior premo tego. Aptent autem imputo. Aptent bene elit eros nisl obruo praemitto si.\n\nPopulus praesent premo quadrum scisco torqueo typicus ut valde. Consectetuer facilisi natu ut valde vero. Defui incassum luptatum valde vel. Blandit esca nobis obruo premo usitas virtus. Camur cogo ea elit eu ibidem nostrud tamen turpis usitas. Damnum fere suscipere ullamcorper.\n\nAutem eros ex ideo loquor rusticus suscipit turpis. Autem genitus hos melior molior nisl sagaciter venio. Aptent et meus mos persto pertineo ratis valde zelus. Acsi aliquip esca humo inhibeo. Brevitas caecus dignissim feugiat immitto in praemitto sagaciter valde volutpat.\n\nAliquip bene dolus eligo neo pagus quia quidne refoveo validus. Caecus dolor natu patria. Eligo elit velit. Camur dignissim dolor magna minim suscipit vulpes. Eum immitto jumentum laoreet os ratis refero saluto tego vereor. Acsi defui enim feugiat lenis loquor minim premo veniam. Abbas cui ex facilisi obruo os premo sed. Lobortis scisco velit.\n\nErat occuro proprius vero vulputate. Abbas defui facilisi gravis ideo interdico typicus vel vero zelus. At dolus eu macto magna occuro odio qui refoveo secundum. Duis nunc tincidunt typicus veniam vulpes. Abbas aliquam at camur haero minim molior tation.\n\nHuic jugis occuro pecus pneum. Eum hos huic loquor luctus molior nisl pala similis vero. Abluo camur natu occuro persto pertineo pneum sino verto. Abbas eligo minim secundum suscipit. Abluo ideo natu olim praesent quis secundum similis suscipere. Adipiscing et ideo melior premo sagaciter typicus. Decet ideo letalis nunc. Acsi luptatum roto wisi.\n\nAbdo amet hos huic iustum quia similis. Haero loquor ymo. Consequat ille os praemitto sagaciter valetudo. Cogo duis ideo neo pertineo pneum saluto. Distineo duis exerci genitus nunc pagus refoveo te. Dolus imputo lobortis pecus secundum turpis. Aliquam at augue capto et laoreet quibus suscipit te vereor.\n\nEt facilisi iriure utrum. Abluo ille praesent quibus sagaciter. Capto eligo hendrerit melior pagus pala. Acsi at esse humo jumentum sudo ut voco. Duis inhibeo meus utrum. Illum oppeto validus. Duis et si ut. Aptent damnum esse gilvus probo. Dolus facilisis lucidus nostrud pneum proprius sed uxor.\n\nAt paratus populus utinam. Autem decet mauris praesent quidem sed ulciscor valde. Elit minim ratis sed velit. Capto nimis paulatim quadrum quidem zelus.\n\n",
            "format": "plain_text",
            "summary": "Aptent minim sino valetudo. Abigo magna uxor. Comis defui mos nobis si. Commodo populus vindico. Dolus eligo elit pala. Commodo dolor facilisi gemino os saluto. Autem dolore facilisi pertineo praemitto quis si suscipere. Comis distineo haero obruo occuro pneum. Duis enim hos mauris suscipere. Et persto sed. Et humo letalis metuo nimis plaga qui zelus. Abbas commodo dolor eligo ibidem nostrud premo si.\n\nAbico haero ibidem illum incassum pagus refero saluto. Gilvus natu saluto sino valde ymo. Comis duis eligo esca eum iriure letalis nulla pneum valetudo. Dolore esse jumentum velit wisi.\n\nPraesent quis si singularis usitas. Abbas dolus interdico natu probo qui vulputate. Iusto lucidus saluto valde. Aptent eligo erat exerci hos jugis natu vereor. Duis feugiat suscipit. Huic imputo lucidus qui refoveo saepius similis.\n\nDistineo iusto jumentum modo pecus voco. Aliquam consectetuer cui eum importunus luptatum molior tamen venio. Commodo nobis valde. Appellatio at caecus distineo dolus iustum quis sagaciter sit vulputate. Abbas nisl nulla os pagus wisi. Importunus nimis occuro vicis. Commoveo esca lenis obruo. Facilisis laoreet molior premo tego. Aptent autem imputo. Aptent bene elit eros nisl obruo praemitto si.\n\nPopulus praesent premo quadrum scisco torqueo typicus ut valde. Consectetuer facilisi natu ut valde vero. Defui incassum luptatum valde vel. Blandit esca nobis obruo premo usitas virtus. Camur cogo ea elit eu ibidem nostrud tamen turpis usitas. Damnum fere suscipere ullamcorper.\n\nAutem eros ex ideo loquor rusticus suscipit turpis. Autem genitus hos melior molior nisl sagaciter venio. Aptent et meus mos persto pertineo ratis valde zelus. Acsi aliquip esca humo inhibeo. Brevitas caecus dignissim feugiat immitto in praemitto sagaciter valde volutpat.\n\nAliquip bene dolus eligo neo pagus quia quidne refoveo validus. Caecus dolor natu patria. Eligo elit velit. Camur dignissim dolor magna minim suscipit vulpes. Eum immitto jumentum laoreet os ratis refero saluto tego vereor. Acsi defui enim feugiat lenis loquor minim premo veniam. Abbas cui ex facilisi obruo os premo sed. Lobortis scisco velit.\n\nErat occuro proprius vero vulputate. Abbas defui facilisi gravis ideo interdico typicus vel vero zelus. At dolus eu macto magna occuro odio qui refoveo secundum. Duis nunc tincidunt typicus veniam vulpes. Abbas aliquam at camur haero minim molior tation.\n\nHuic jugis occuro pecus pneum. Eum hos huic loquor luctus molior nisl pala similis vero. Abluo camur natu occuro persto pertineo pneum sino verto. Abbas eligo minim secundum suscipit. Abluo ideo natu olim praesent quis secundum similis suscipere. Adipiscing et ideo melior premo sagaciter typicus. Decet ideo letalis nunc. Acsi luptatum roto wisi.\n\nAbdo amet hos huic iustum quia similis. Haero loquor ymo. Consequat ille os praemitto sagaciter valetudo. Cogo duis ideo neo pertineo pneum saluto. Distineo duis exerci genitus nunc pagus refoveo te. Dolus imputo lobortis pecus secundum turpis. Aliquam at augue capto et laoreet quibus suscipit te vereor.\n\nEt facilisi iriure utrum. Abluo ille praesent quibus sagaciter. Capto eligo hendrerit melior pagus pala. Acsi at esse humo jumentum sudo ut voco. Duis inhibeo meus utrum. Illum oppeto validus. Duis et si ut. Aptent damnum esse gilvus probo. Dolus facilisis lucidus nostrud pneum proprius sed uxor.\n\nAt paratus populus utinam. Autem decet mauris praesent quidem sed ulciscor valde. Elit minim ratis sed velit. Capto nimis paulatim quadrum quidem zelus.\n\n"
        }
    ],
    "field_image": [
        {
            "alt": "Consequat si tamen. Aliquip eu ex illum luptatum nimis pagus ut.",
            "title": "Commoveo dolore esca hendrerit nobis nulla plaga rusticus vereor.",
            "width": 414,
            "height": 600,
            "target_type": "file",
            "target_uuid": "31fd871f-6230-4a4a-aa11-eb1f3e8c948d"
        }
    ],
    "field_tags": [
        {
            "target_type": "taxonomy_term",
            "target_uuid": "74e6ff3b-f97f-4586-8837-9b4f3d1e6d00"
        },
        {
            "target_type": "taxonomy_term",
            "target_uuid": "2973b9b4-fbe5-451a-a09f-b1ea4fb3a7a1"
        },
        {
            "target_type": "taxonomy_term",
            "target_uuid": "39f767d9-2c7a-4f96-9dec-7a89a7d74375"
        },
        {
            "target_type": "taxonomy_term",
            "target_uuid": "2735692b-ca41-45fc-bafe-27b62175b130"
        },
        {
            "target_type": "taxonomy_term",
            "target_uuid": "94ea31fa-b5e4-41b0-be08-12ed918af715"
        }
    ]
}