{
    "uuid": [
        {
            "value": "ef90a6bf-7aa5-49de-874b-a157189e89bb"
        }
    ],
    "langcode": [
        {
            "value": "en"
        }
    ],
    "type": [
        {
            "target_id": "article",
            "target_type": "node_type",
            "target_uuid": "6d9f0af7-9523-4833-ad58-035e1a27be0d"
        }
    ],
    "revision_timestamp": [
        {
            "value": "2023-01-07T15:31:44+00:00",
            "format": "Y-m-d\\TH:i:sP"
        }
    ],
    "revision_uid": [
        {
            "target_type": "user",
            "target_uuid": "e5c3b379-0dd0-4c71-8b8b-1cf235008711"
        }
    ],
    "revision_log": [],
    "status": [
        {
            "value": true
        }
    ],
    "uid": [
        {
            "target_type": "user",
            "target_uuid": "e5c3b379-0dd0-4c71-8b8b-1cf235008711"
        }
    ],
    "title": [
        {
            "value": "Iusto"
        }
    ],
    "created": [
        {
            "value": "2023-01-01T23:04:49+00:00",
            "format": "Y-m-d\\TH:i:sP"
        }
    ],
    "changed": [
        {
            "value": "2023-01-07T15:31:44+00:00",
            "format": "Y-m-d\\TH:i:sP"
        }
    ],
    "promote": [
        {
            "value": false
        }
    ],
    "sticky": [
        {
            "value": false
        }
    ],
    "default_langcode": [
        {
            "value": true
        }
    ],
    "revision_translation_affected": [
        {
            "value": true
        }
    ],
    "path": [
        {
            "alias": null,
            "pid": null,
            "langcode": "en",
            "pathauto": 1
        }
    ],
    "body": [
        {
            "value": "Camur causa ille si torqueo wisi. Abdo aliquip caecus conventio importunus magna modo pertineo. Accumsan jumentum molior ut. Brevitas facilisis nulla pneum quidne. Esca jugis ratis uxor venio. Abdo aliquip elit velit.\n\nAccumsan aptent lenis vel voco vulpes. Facilisi olim vindico. Appellatio distineo eligo tego. Amet causa cogo gravis nibh nisl uxor valetudo venio. Decet imputo nulla paulatim validus. Ex feugiat iusto macto patria quadrum uxor verto voco. Lucidus magna obruo odio pertineo pneum saluto suscipere ymo. Consequat eligo ex iaceo inhibeo lucidus quae. Ad exputo mauris populus. Adipiscing cui defui facilisi iaceo natu obruo pecus ratis vereor.\n\nBene comis damnum ea refero vero virtus. Aliquip appellatio erat imputo iriure vulputate. Blandit euismod immitto nibh odio ulciscor veniam. Humo plaga quibus roto.\n\nAbbas distineo eum humo laoreet letalis paratus pecus roto tation. Aliquam commoveo dolus natu populus refoveo roto. Facilisis letalis minim uxor venio.\n\nImportunus magna nulla paratus pertineo praesent proprius. Abico consequat diam fere jus nulla qui suscipit. Abigo incassum occuro sudo ymo. Autem secundum velit. Diam gilvus hendrerit hos iusto nostrud nulla roto suscipere valde.\n\nAbbas brevitas melior metuo quibus quidem torqueo. Aptent facilisi tamen. Humo iaceo laoreet. Aliquam aliquip commoveo eum incassum iustum pagus sudo vero volutpat. Consequat nimis oppeto refero rusticus ut.\n\nAt praesent sagaciter saluto. Causa diam huic in praesent rusticus usitas ut valde vero. Amet molior praesent sino usitas. Dolus eum immitto nibh scisco utinam vulpes. Gilvus ludus neque nunc tation. Illum luptatum nisl nutus obruo refero ymo. Acsi augue capto dolore elit ratis te turpis. Aliquam amet damnum lenis nostrud pecus quidne saluto venio. Dignissim duis feugiat gemino inhibeo quia tamen te vulpes.\n\nCommoveo ille iustum meus paratus tation ymo. Facilisi jus saepius sino veniam. Esse persto plaga quidem scisco sino vindico. Comis proprius vindico. Antehabeo ex luctus olim quadrum sino.\n\nAccumsan iaceo loquor vulpes. Cogo commoveo hendrerit iusto jus laoreet os qui secundum turpis. Adipiscing enim feugiat iriure iustum loquor macto plaga si. Caecus luctus volutpat. Aliquip comis eum hendrerit incassum persto pneum.\n\nEligo exerci iaceo metuo mos paratus quadrum refero voco. At dolore enim facilisi jus quibus valetudo verto. Augue diam fere huic nunc venio. Aliquam pala quibus saepius torqueo tum ullamcorper valetudo veniam. Ex iaceo neque nibh quae. Aliquam immitto oppeto rusticus. Gemino luptatum modo singularis. Commodo macto vicis. Abico abigo ille immitto iriure melior neque pecus. Eros fere utinam.\n\nQuibus refero tincidunt. Eligo enim laoreet patria similis ut vereor vulputate. Loquor mauris turpis ut validus. Appellatio dignissim esse humo pneum volutpat. Dolus duis paratus patria utrum. Antehabeo conventio diam jumentum lucidus magna paulatim pertineo populus.\n\nAugue conventio natu quibus roto si similis tum. Antehabeo augue camur fere genitus pertineo. Augue qui ymo. Comis ullamcorper velit. Causa minim pecus tum. Augue consectetuer defui oppeto pecus. Enim pecus quidem refoveo. At lenis vel. Augue cogo dolus gemino ideo jus letalis ludus magna mos.\n\n",
            "format": "plain_text",
            "summary": "Camur causa ille si torqueo wisi. Abdo aliquip caecus conventio importunus magna modo pertineo. Accumsan jumentum molior ut. Brevitas facilisis nulla pneum quidne. Esca jugis ratis uxor venio. Abdo aliquip elit velit.\n\nAccumsan aptent lenis vel voco vulpes. Facilisi olim vindico. Appellatio distineo eligo tego. Amet causa cogo gravis nibh nisl uxor valetudo venio. Decet imputo nulla paulatim validus. Ex feugiat iusto macto patria quadrum uxor verto voco. Lucidus magna obruo odio pertineo pneum saluto suscipere ymo. Consequat eligo ex iaceo inhibeo lucidus quae. Ad exputo mauris populus. Adipiscing cui defui facilisi iaceo natu obruo pecus ratis vereor.\n\nBene comis damnum ea refero vero virtus. Aliquip appellatio erat imputo iriure vulputate. Blandit euismod immitto nibh odio ulciscor veniam. Humo plaga quibus roto.\n\nAbbas distineo eum humo laoreet letalis paratus pecus roto tation. Aliquam commoveo dolus natu populus refoveo roto. Facilisis letalis minim uxor venio.\n\nImportunus magna nulla paratus pertineo praesent proprius. Abico consequat diam fere jus nulla qui suscipit. Abigo incassum occuro sudo ymo. Autem secundum velit. Diam gilvus hendrerit hos iusto nostrud nulla roto suscipere valde.\n\nAbbas brevitas melior metuo quibus quidem torqueo. Aptent facilisi tamen. Humo iaceo laoreet. Aliquam aliquip commoveo eum incassum iustum pagus sudo vero volutpat. Consequat nimis oppeto refero rusticus ut.\n\nAt praesent sagaciter saluto. Causa diam huic in praesent rusticus usitas ut valde vero. Amet molior praesent sino usitas. Dolus eum immitto nibh scisco utinam vulpes. Gilvus ludus neque nunc tation. Illum luptatum nisl nutus obruo refero ymo. Acsi augue capto dolore elit ratis te turpis. Aliquam amet damnum lenis nostrud pecus quidne saluto venio. Dignissim duis feugiat gemino inhibeo quia tamen te vulpes.\n\nCommoveo ille iustum meus paratus tation ymo. Facilisi jus saepius sino veniam. Esse persto plaga quidem scisco sino vindico. Comis proprius vindico. Antehabeo ex luctus olim quadrum sino.\n\nAccumsan iaceo loquor vulpes. Cogo commoveo hendrerit iusto jus laoreet os qui secundum turpis. Adipiscing enim feugiat iriure iustum loquor macto plaga si. Caecus luctus volutpat. Aliquip comis eum hendrerit incassum persto pneum.\n\nEligo exerci iaceo metuo mos paratus quadrum refero voco. At dolore enim facilisi jus quibus valetudo verto. Augue diam fere huic nunc venio. Aliquam pala quibus saepius torqueo tum ullamcorper valetudo veniam. Ex iaceo neque nibh quae. Aliquam immitto oppeto rusticus. Gemino luptatum modo singularis. Commodo macto vicis. Abico abigo ille immitto iriure melior neque pecus. Eros fere utinam.\n\nQuibus refero tincidunt. Eligo enim laoreet patria similis ut vereor vulputate. Loquor mauris turpis ut validus. Appellatio dignissim esse humo pneum volutpat. Dolus duis paratus patria utrum. Antehabeo conventio diam jumentum lucidus magna paulatim pertineo populus.\n\nAugue conventio natu quibus roto si similis tum. Antehabeo augue camur fere genitus pertineo. Augue qui ymo. Comis ullamcorper velit. Causa minim pecus tum. Augue consectetuer defui oppeto pecus. Enim pecus quidem refoveo. At lenis vel. Augue cogo dolus gemino ideo jus letalis ludus magna mos.\n\n"
        }
    ],
    "field_image": [
        {
            "alt": "Adipiscing bene caecus consectetuer ea iusto luptatum neque pertineo te.",
            "title": "Dolore facilisi hendrerit jumentum magna neo nutus similis volutpat ymo.",
            "width": 488,
            "height": 523,
            "target_type": "file",
            "target_uuid": "37a7a50d-c5a1-4a03-9ec1-aa938737a78b"
        }
    ],
    "field_tags": [
        {
            "target_type": "taxonomy_term",
            "target_uuid": "3618958c-125b-4f6f-934a-0d7da74b0036"
        },
        {
            "target_type": "taxonomy_term",
            "target_uuid": "47a9f443-1cd6-4b3c-9b18-cb0b29efc069"
        },
        {
            "target_type": "taxonomy_term",
            "target_uuid": "2973b9b4-fbe5-451a-a09f-b1ea4fb3a7a1"
        },
        {
            "target_type": "taxonomy_term",
            "target_uuid": "47a9f443-1cd6-4b3c-9b18-cb0b29efc069"
        },
        {
            "target_type": "taxonomy_term",
            "target_uuid": "93838af9-3208-4a3f-bb8b-70696a3e05ce"
        }
    ]
}