{
    "uuid": [
        {
            "value": "fcc8bb1c-803c-4005-a7ed-d4f9e2ed0761"
        }
    ],
    "langcode": [
        {
            "value": "en"
        }
    ],
    "type": [
        {
            "target_id": "article",
            "target_type": "node_type",
            "target_uuid": "6d9f0af7-9523-4833-ad58-035e1a27be0d"
        }
    ],
    "revision_timestamp": [
        {
            "value": "2023-01-07T11:30:25+00:00",
            "format": "Y-m-d\\TH:i:sP"
        }
    ],
    "revision_uid": [
        {
            "target_type": "user",
            "target_uuid": "e5c3b379-0dd0-4c71-8b8b-1cf235008711"
        }
    ],
    "revision_log": [],
    "status": [
        {
            "value": true
        }
    ],
    "uid": [
        {
            "target_type": "user",
            "target_uuid": "e5c3b379-0dd0-4c71-8b8b-1cf235008711"
        }
    ],
    "title": [
        {
            "value": "Enim Iusto Lenis Quis"
        }
    ],
    "created": [
        {
            "value": "2023-01-06T11:01:17+00:00",
            "format": "Y-m-d\\TH:i:sP"
        }
    ],
    "changed": [
        {
            "value": "2023-01-07T11:30:25+00:00",
            "format": "Y-m-d\\TH:i:sP"
        }
    ],
    "promote": [
        {
            "value": false
        }
    ],
    "sticky": [
        {
            "value": false
        }
    ],
    "default_langcode": [
        {
            "value": true
        }
    ],
    "revision_translation_affected": [
        {
            "value": true
        }
    ],
    "path": [
        {
            "alias": "\/enim-iusto-lenis-quis",
            "langcode": "en",
            "pathauto": 1
        }
    ],
    "body": [
        {
            "value": "Aliquam immitto persto refoveo si singularis ut. Abluo causa feugiat hendrerit ibidem metuo tamen tego turpis voco. Ideo iusto melior pala persto. Adipiscing blandit duis eros facilisi gravis olim similis usitas vicis. Aliquip et hendrerit neo nobis.\n\nEnim feugiat quibus. Conventio luptatum metuo plaga. Abdo consequat conventio diam euismod gemino mauris neo occuro vindico. Dolore ex ideo iusto pertineo refoveo torqueo typicus usitas vindico.\n\nAcsi decet exputo luptatum nostrud pala sed similis tego. Augue eligo neo proprius quis refoveo tation utrum vulputate ymo. Illum importunus metuo praemitto probo singularis tamen tincidunt typicus virtus. Accumsan brevitas dolore dolus elit ludus pneum qui rusticus suscipere. Abico blandit dolor in virtus. Antehabeo dignissim facilisi natu.\n\nCapto os sino. Commodo elit luctus saepius usitas virtus. Defui dolus erat genitus gravis laoreet vindico. At ea laoreet melior paratus patria sino utrum voco. Distineo laoreet molior nisl qui quibus ratis tego valetudo. Amet autem eu gilvus meus te. Abluo caecus ea esca iaceo iustum volutpat. Abdo iaceo loquor neo nostrud patria populus secundum ulciscor utrum.\n\nExerci feugiat hos ille meus. Capto commoveo decet gilvus iusto ludus nobis quibus singularis. Gilvus lobortis paulatim quidem virtus wisi zelus. Accumsan commoveo lenis. Aliquam aptent dignissim dolor pagus pertineo venio. Et gravis in os plaga. Damnum elit hendrerit interdico jumentum minim olim praesent tego veniam.\n\nEnim hos iriure neo patria tamen. Distineo enim ludus macto metuo pala venio voco. Aliquip ludus qui quidem vicis. Aliquip bene blandit comis duis ille iriure. Abdo inhibeo nulla typicus voco. Capto neque olim. Minim neo valde. Cogo comis esca qui scisco similis utinam vereor. Ad autem comis feugiat ille magna refoveo velit.\n\nAptent dolus erat fere hendrerit ludus mos pertineo si valetudo. Abluo distineo eros hos modo olim. Obruo tincidunt ymo. Duis gravis jus praesent premo. Importunus paratus valetudo. Ad commoveo damnum illum jumentum praesent vicis.\n\nEuismod exputo ibidem luptatum paulatim validus vindico voco. Abico incassum vindico. Gilvus huic imputo praemitto qui secundum tum zelus. Defui exerci paulatim. Causa feugiat iriure modo oppeto quibus scisco suscipere.\n\nCamur ea ex illum importunus ludus nutus quadrum. Neque quibus saluto scisco suscipere verto voco wisi. Consequat defui enim incassum obruo quis valetudo vicis vindico. Erat luptatum quidem suscipere. Appellatio dolus interdico iusto oppeto pertineo utinam velit. Abico aliquam eligo exerci iustum lucidus nisl proprius qui. Gravis lucidus nimis nulla. Euismod minim nimis vulpes.\n\nAd consectetuer consequat duis ideo interdico natu odio qui voco. Abluo causa ea euismod gilvus iaceo illum proprius uxor vindico. Augue eum utinam. Abluo cui dolus importunus iustum pala patria pertineo probo sudo.\n\nCamur ex ille jus magna. Camur cogo eu mos oppeto persto proprius venio. Amet at caecus enim euismod importunus nostrud quia vereor. Metuo molior os quae. Brevitas nulla sed. Capto exerci letalis nostrud quis vero virtus ymo. Aliquam aliquip erat facilisis tincidunt uxor verto. Meus pecus probo saepius. Comis ea mauris patria. Comis duis exerci fere loquor macto occuro tamen utrum.\n\nConventio praesent quibus. Abigo ea euismod meus premo. Brevitas consectetuer consequat ea ille metuo nimis nulla pneum refoveo. Duis immitto iusto odio vel ymo. Cui patria ulciscor validus. Accumsan dolor immitto iusto neo nunc quibus saepius valetudo vero.\n\n",
            "format": "plain_text",
            "summary": "Aliquam immitto persto refoveo si singularis ut. Abluo causa feugiat hendrerit ibidem metuo tamen tego turpis voco. Ideo iusto melior pala persto. Adipiscing blandit duis eros facilisi gravis olim similis usitas vicis. Aliquip et hendrerit neo nobis.\n\nEnim feugiat quibus. Conventio luptatum metuo plaga. Abdo consequat conventio diam euismod gemino mauris neo occuro vindico. Dolore ex ideo iusto pertineo refoveo torqueo typicus usitas vindico.\n\nAcsi decet exputo luptatum nostrud pala sed similis tego. Augue eligo neo proprius quis refoveo tation utrum vulputate ymo. Illum importunus metuo praemitto probo singularis tamen tincidunt typicus virtus. Accumsan brevitas dolore dolus elit ludus pneum qui rusticus suscipere. Abico blandit dolor in virtus. Antehabeo dignissim facilisi natu.\n\nCapto os sino. Commodo elit luctus saepius usitas virtus. Defui dolus erat genitus gravis laoreet vindico. At ea laoreet melior paratus patria sino utrum voco. Distineo laoreet molior nisl qui quibus ratis tego valetudo. Amet autem eu gilvus meus te. Abluo caecus ea esca iaceo iustum volutpat. Abdo iaceo loquor neo nostrud patria populus secundum ulciscor utrum.\n\nExerci feugiat hos ille meus. Capto commoveo decet gilvus iusto ludus nobis quibus singularis. Gilvus lobortis paulatim quidem virtus wisi zelus. Accumsan commoveo lenis. Aliquam aptent dignissim dolor pagus pertineo venio. Et gravis in os plaga. Damnum elit hendrerit interdico jumentum minim olim praesent tego veniam.\n\nEnim hos iriure neo patria tamen. Distineo enim ludus macto metuo pala venio voco. Aliquip ludus qui quidem vicis. Aliquip bene blandit comis duis ille iriure. Abdo inhibeo nulla typicus voco. Capto neque olim. Minim neo valde. Cogo comis esca qui scisco similis utinam vereor. Ad autem comis feugiat ille magna refoveo velit.\n\nAptent dolus erat fere hendrerit ludus mos pertineo si valetudo. Abluo distineo eros hos modo olim. Obruo tincidunt ymo. Duis gravis jus praesent premo. Importunus paratus valetudo. Ad commoveo damnum illum jumentum praesent vicis.\n\nEuismod exputo ibidem luptatum paulatim validus vindico voco. Abico incassum vindico. Gilvus huic imputo praemitto qui secundum tum zelus. Defui exerci paulatim. Causa feugiat iriure modo oppeto quibus scisco suscipere.\n\nCamur ea ex illum importunus ludus nutus quadrum. Neque quibus saluto scisco suscipere verto voco wisi. Consequat defui enim incassum obruo quis valetudo vicis vindico. Erat luptatum quidem suscipere. Appellatio dolus interdico iusto oppeto pertineo utinam velit. Abico aliquam eligo exerci iustum lucidus nisl proprius qui. Gravis lucidus nimis nulla. Euismod minim nimis vulpes.\n\nAd consectetuer consequat duis ideo interdico natu odio qui voco. Abluo causa ea euismod gilvus iaceo illum proprius uxor vindico. Augue eum utinam. Abluo cui dolus importunus iustum pala patria pertineo probo sudo.\n\nCamur ex ille jus magna. Camur cogo eu mos oppeto persto proprius venio. Amet at caecus enim euismod importunus nostrud quia vereor. Metuo molior os quae. Brevitas nulla sed. Capto exerci letalis nostrud quis vero virtus ymo. Aliquam aliquip erat facilisis tincidunt uxor verto. Meus pecus probo saepius. Comis ea mauris patria. Comis duis exerci fere loquor macto occuro tamen utrum.\n\nConventio praesent quibus. Abigo ea euismod meus premo. Brevitas consectetuer consequat ea ille metuo nimis nulla pneum refoveo. Duis immitto iusto odio vel ymo. Cui patria ulciscor validus. Accumsan dolor immitto iusto neo nunc quibus saepius valetudo vero.\n\n"
        }
    ],
    "field_image": [
        {
            "alt": "Abico defui dolore suscipere tation wisi.",
            "title": "Damnum et feugiat. Brevitas damnum eu gemino metuo nobis si torqueo valetudo.",
            "width": 435,
            "height": 429,
            "target_type": "file",
            "target_uuid": "cb89fc2c-df7d-4c04-9a69-63142897c5ba"
        }
    ],
    "field_tags": [
        {
            "target_type": "taxonomy_term",
            "target_uuid": "6c253423-0acd-44f6-aa8d-de74509b1654"
        },
        {
            "target_type": "taxonomy_term",
            "target_uuid": "3aad2888-95b3-4ad8-8d39-80a0f8c1f20b"
        },
        {
            "target_type": "taxonomy_term",
            "target_uuid": "47a9f443-1cd6-4b3c-9b18-cb0b29efc069"
        },
        {
            "target_type": "taxonomy_term",
            "target_uuid": "3aad2888-95b3-4ad8-8d39-80a0f8c1f20b"
        },
        {
            "target_type": "taxonomy_term",
            "target_uuid": "2735692b-ca41-45fc-bafe-27b62175b130"
        }
    ]
}