{
    "uuid": [
        {
            "value": "eeb6cf40-1dd0-4b1e-8f9d-6a068188ce6a"
        }
    ],
    "langcode": [
        {
            "value": "en"
        }
    ],
    "type": [
        {
            "target_id": "article",
            "target_type": "node_type",
            "target_uuid": "6d9f0af7-9523-4833-ad58-035e1a27be0d"
        }
    ],
    "revision_timestamp": [
        {
            "value": "2023-01-07T15:35:01+00:00",
            "format": "Y-m-d\\TH:i:sP"
        }
    ],
    "revision_uid": [
        {
            "target_type": "user",
            "target_uuid": "e5c3b379-0dd0-4c71-8b8b-1cf235008711"
        }
    ],
    "revision_log": [],
    "status": [
        {
            "value": true
        }
    ],
    "uid": [
        {
            "target_type": "user",
            "target_uuid": "e5c3b379-0dd0-4c71-8b8b-1cf235008711"
        }
    ],
    "title": [
        {
            "value": "Nisl"
        }
    ],
    "created": [
        {
            "value": "2023-01-05T04:35:48+00:00",
            "format": "Y-m-d\\TH:i:sP"
        }
    ],
    "changed": [
        {
            "value": "2023-01-07T15:35:01+00:00",
            "format": "Y-m-d\\TH:i:sP"
        }
    ],
    "promote": [
        {
            "value": true
        }
    ],
    "sticky": [
        {
            "value": false
        }
    ],
    "default_langcode": [
        {
            "value": true
        }
    ],
    "revision_translation_affected": [
        {
            "value": true
        }
    ],
    "path": [
        {
            "alias": null,
            "pid": null,
            "langcode": "en",
            "pathauto": 1
        }
    ],
    "body": [
        {
            "value": "Abdo conventio damnum defui distineo humo immitto jugis. Abdo capto jugis oppeto sagaciter. Brevitas cogo cui dolus hos jumentum metuo probo scisco te.\n\nAbigo ea nulla verto. Abluo augue brevitas consequat esse iriure. Camur hendrerit ideo loquor os ymo. Feugiat probo sed suscipere vero. Dolore luctus os utinam.\n\nEligo jus nisl obruo praemitto praesent qui. Laoreet natu olim populus sed. Comis inhibeo mauris neo nulla nunc os plaga ratis. Augue elit ex gravis nutus oppeto pertineo tation vulpes. Decet genitus jugis proprius ut. Hos occuro persto ratis. Genitus nutus proprius. Abigo huic minim obruo occuro quae suscipere torqueo.\n\nConsequat facilisi iusto nunc pneum ullamcorper zelus. Abbas elit loquor nostrud. Amet distineo fere. Eum interdico olim paratus vicis. Autem ex exerci hos huic jugis lenis sino suscipit uxor.\n\nAccumsan dolor fere immitto lobortis oppeto si. Humo inhibeo modo praemitto sudo validus. Dignissim eu in luptatum mos patria praesent sit. Abluo duis esse iustum letalis neo probo valde vel. Abbas acsi dolor iusto nobis paratus scisco turpis valde.\n\nAdipiscing inhibeo nobis patria pertineo probo vereor. Abbas blandit exputo ille oppeto plaga roto sit. Abluo acsi amet augue consectetuer decet luctus valetudo vindico.\n\nEsse exerci genitus iriure nibh roto saluto. Erat pagus patria secundum sino volutpat. Abdo abico illum minim qui quis valetudo verto. Imputo nulla suscipere tego. Aptent neo singularis. Exputo facilisis gemino lucidus macto mos nimis vulpes. Dolus exerci neo nimis nutus quidne valetudo vicis vulpes. Bene causa jugis jumentum neo persto probo.\n\nElit enim eu nibh. Consectetuer gemino hendrerit ille letalis luctus neo quidem secundum suscipit. Accumsan antehabeo conventio eligo modo secundum vereor verto virtus. Inhibeo nutus occuro plaga proprius ratis validus. Capto causa neque qui saepius vindico. Exputo mos quae quidem tum venio. Commoveo nimis oppeto pertineo.\n\nConventio eum ille mauris pneum tincidunt. Abdo luptatum molior os quia saepius saluto uxor. Augue mauris quia. Exputo facilisis paratus pertineo praesent sed. Esca letalis nunc pala. Haero occuro pecus. Cogo dolor eros vindico. Eligo erat modo sit veniam. Bene camur exputo iaceo laoreet neque sed.\n\nPlaga saluto secundum. Causa distineo eligo humo jus melior praesent suscipit te ut. Accumsan cui modo te voco. Blandit gilvus ludus pagus pecus plaga rusticus sino. Defui gilvus inhibeo modo premo similis tamen ulciscor vereor vindico. Commodo eligo neque pneum quia.\n\nAccumsan melior quae. Causa modo ullamcorper. Abbas elit facilisis nulla quadrum quidem sit. Facilisi ideo os virtus vulpes zelus. Antehabeo defui dolor eligo eu quibus si. Gravis ille in iusto macto mos quis roto vero. At consectetuer jugis lucidus. Ad aliquam commoveo facilisi iaceo ludus sino torqueo vel ymo.\n\nAdipiscing conventio damnum typicus. Augue facilisis ille magna metuo quidne. Abico brevitas ideo iustum mauris molior natu nobis scisco. Aliquam feugiat interdico pneum ulciscor vindico. Commoveo in incassum pertineo premo typicus vulputate. Augue genitus haero ille odio populus quadrum quis valetudo venio. Facilisi feugiat ille interdico probo. Minim quae qui tamen volutpat. Abluo gemino gilvus occuro paratus pecus praesent sit valde wisi.\n\n",
            "format": "plain_text",
            "summary": "Abdo conventio damnum defui distineo humo immitto jugis. Abdo capto jugis oppeto sagaciter. Brevitas cogo cui dolus hos jumentum metuo probo scisco te.\n\nAbigo ea nulla verto. Abluo augue brevitas consequat esse iriure. Camur hendrerit ideo loquor os ymo. Feugiat probo sed suscipere vero. Dolore luctus os utinam.\n\nEligo jus nisl obruo praemitto praesent qui. Laoreet natu olim populus sed. Comis inhibeo mauris neo nulla nunc os plaga ratis. Augue elit ex gravis nutus oppeto pertineo tation vulpes. Decet genitus jugis proprius ut. Hos occuro persto ratis. Genitus nutus proprius. Abigo huic minim obruo occuro quae suscipere torqueo.\n\nConsequat facilisi iusto nunc pneum ullamcorper zelus. Abbas elit loquor nostrud. Amet distineo fere. Eum interdico olim paratus vicis. Autem ex exerci hos huic jugis lenis sino suscipit uxor.\n\nAccumsan dolor fere immitto lobortis oppeto si. Humo inhibeo modo praemitto sudo validus. Dignissim eu in luptatum mos patria praesent sit. Abluo duis esse iustum letalis neo probo valde vel. Abbas acsi dolor iusto nobis paratus scisco turpis valde.\n\nAdipiscing inhibeo nobis patria pertineo probo vereor. Abbas blandit exputo ille oppeto plaga roto sit. Abluo acsi amet augue consectetuer decet luctus valetudo vindico.\n\nEsse exerci genitus iriure nibh roto saluto. Erat pagus patria secundum sino volutpat. Abdo abico illum minim qui quis valetudo verto. Imputo nulla suscipere tego. Aptent neo singularis. Exputo facilisis gemino lucidus macto mos nimis vulpes. Dolus exerci neo nimis nutus quidne valetudo vicis vulpes. Bene causa jugis jumentum neo persto probo.\n\nElit enim eu nibh. Consectetuer gemino hendrerit ille letalis luctus neo quidem secundum suscipit. Accumsan antehabeo conventio eligo modo secundum vereor verto virtus. Inhibeo nutus occuro plaga proprius ratis validus. Capto causa neque qui saepius vindico. Exputo mos quae quidem tum venio. Commoveo nimis oppeto pertineo.\n\nConventio eum ille mauris pneum tincidunt. Abdo luptatum molior os quia saepius saluto uxor. Augue mauris quia. Exputo facilisis paratus pertineo praesent sed. Esca letalis nunc pala. Haero occuro pecus. Cogo dolor eros vindico. Eligo erat modo sit veniam. Bene camur exputo iaceo laoreet neque sed.\n\nPlaga saluto secundum. Causa distineo eligo humo jus melior praesent suscipit te ut. Accumsan cui modo te voco. Blandit gilvus ludus pagus pecus plaga rusticus sino. Defui gilvus inhibeo modo premo similis tamen ulciscor vereor vindico. Commodo eligo neque pneum quia.\n\nAccumsan melior quae. Causa modo ullamcorper. Abbas elit facilisis nulla quadrum quidem sit. Facilisi ideo os virtus vulpes zelus. Antehabeo defui dolor eligo eu quibus si. Gravis ille in iusto macto mos quis roto vero. At consectetuer jugis lucidus. Ad aliquam commoveo facilisi iaceo ludus sino torqueo vel ymo.\n\nAdipiscing conventio damnum typicus. Augue facilisis ille magna metuo quidne. Abico brevitas ideo iustum mauris molior natu nobis scisco. Aliquam feugiat interdico pneum ulciscor vindico. Commoveo in incassum pertineo premo typicus vulputate. Augue genitus haero ille odio populus quadrum quis valetudo venio. Facilisi feugiat ille interdico probo. Minim quae qui tamen volutpat. Abluo gemino gilvus occuro paratus pecus praesent sit valde wisi.\n\n"
        }
    ],
    "field_image": [
        {
            "alt": "Laoreet si typicus. Accumsan appellatio bene commoveo huic ibidem natu nimis nostrud paratus.",
            "title": "Conventio dignissim haero mauris valetudo.",
            "width": 401,
            "height": 352,
            "target_type": "file",
            "target_uuid": "fd7a1ceb-c128-4fd6-80ad-096da9e7ffba"
        }
    ],
    "field_tags": [
        {
            "target_type": "taxonomy_term",
            "target_uuid": "48bd2b5d-988e-4f5e-a40c-a9b9e922b917"
        },
        {
            "target_type": "taxonomy_term",
            "target_uuid": "eb8b8f80-429f-44df-8bb3-8c1d7e6514fe"
        },
        {
            "target_type": "taxonomy_term",
            "target_uuid": "4dcaa2bf-f9fe-4213-a72c-a2f6a45f4761"
        },
        {
            "target_type": "taxonomy_term",
            "target_uuid": "dd125db3-2899-4312-9fff-574798f01668"
        },
        {
            "target_type": "taxonomy_term",
            "target_uuid": "dfa4804a-f9af-4eff-829d-d4e7b56fea15"
        }
    ]
}