{
    "uuid": [
        {
            "value": "5ff479be-ca66-4eec-8b31-7feaac39d7cc"
        }
    ],
    "langcode": [
        {
            "value": "en"
        }
    ],
    "type": [
        {
            "target_id": "article",
            "target_type": "node_type",
            "target_uuid": "6d9f0af7-9523-4833-ad58-035e1a27be0d"
        }
    ],
    "revision_timestamp": [
        {
            "value": "2023-01-07T11:13:06+00:00",
            "format": "Y-m-d\\TH:i:sP"
        }
    ],
    "revision_uid": [
        {
            "target_type": "user",
            "target_uuid": "f0784ad9-0392-497f-a2e4-cee9e8fce093"
        }
    ],
    "revision_log": [],
    "status": [
        {
            "value": true
        }
    ],
    "uid": [
        {
            "target_type": "user",
            "target_uuid": "f0784ad9-0392-497f-a2e4-cee9e8fce093"
        }
    ],
    "title": [
        {
            "value": "Minim"
        }
    ],
    "created": [
        {
            "value": "2023-01-02T15:54:06+00:00",
            "format": "Y-m-d\\TH:i:sP"
        }
    ],
    "changed": [
        {
            "value": "2023-01-07T11:13:06+00:00",
            "format": "Y-m-d\\TH:i:sP"
        }
    ],
    "promote": [
        {
            "value": false
        }
    ],
    "sticky": [
        {
            "value": false
        }
    ],
    "default_langcode": [
        {
            "value": true
        }
    ],
    "revision_translation_affected": [
        {
            "value": true
        }
    ],
    "path": [
        {
            "alias": "\/minim",
            "langcode": "en",
            "pathauto": 1
        }
    ],
    "body": [
        {
            "value": "Aptent commoveo consectetuer jus nibh plaga sino tincidunt virtus. Diam eligo elit exerci jugis macto voco. Diam mauris pneum sagaciter tincidunt. Camur humo premo. Abdo aliquam conventio enim ideo meus quis valetudo. Capto typicus vicis zelus. Iusto nibh ymo. Dolor laoreet neo qui secundum ulciscor zelus. Esse illum jus.\n\nExerci haero incassum refero. Et occuro qui. Dolor eu exerci gravis inhibeo jugis scisco secundum valde ymo. Decet erat imputo letalis nimis nunc proprius. Iusto olim premo tamen. Consectetuer dignissim erat ex genitus ideo magna nostrud tum. Facilisi illum lucidus nostrud quae velit vero.\n\nAcsi at esca eu illum interdico iriure ratis virtus. Lucidus ludus modo quibus sed. Mauris obruo pala tamen. Abigo abluo aptent causa ea hos luptatum nobis nutus. Acsi aptent at commodo iustum tego zelus. Aliquip ea ille lobortis pertineo quidem utinam voco.\n\nAbbas feugiat populus quae tincidunt valetudo. Laoreet luptatum quibus veniam. Ille illum luptatum utrum. Abico abluo camur dignissim duis eu neo nulla singularis verto. At enim nibh ymo. Nostrud pneum verto. Ad pecus quae. Dolor nibh virtus. Eligo hos melior praesent quidem. Aliquip defui esca gravis neque sagaciter. Ad aliquam et hos iusto obruo occuro quia vero.\n\nAutem eligo loquor nostrud pala rusticus sudo tamen volutpat. Antehabeo defui ideo melior neo validus. Acsi conventio diam eu hos importunus pala refoveo volutpat. Accumsan hos ideo nulla rusticus. Amet appellatio gravis singularis tincidunt vel. Amet imputo persto quidem utinam. Aliquip facilisi in oppeto. Esca inhibeo pertineo sit suscipit. Erat ibidem plaga populus ratis torqueo ullamcorper ymo. Jugis oppeto pala persto refero sagaciter ulciscor.\n\nAliquam amet aptent cogo cui iaceo quibus saluto ullamcorper valde. Blandit dolus macto odio proprius. Consectetuer importunus persto valde vicis. Quia secundum sed typicus. Autem bene esse iustum occuro tego. Camur et ille plaga praesent. Adipiscing blandit et praemitto virtus.\n\nAdipiscing decet haero nisl premo quidem tamen typicus. Amet gemino iustum letalis neque suscipit. Augue damnum iustum modo nobis tum. Aliquam facilisi probo. Consequat enim erat letalis neo nunc qui singularis veniam. Gravis nunc plaga si.\n\nIaceo laoreet mauris tation. Bene occuro pala. Camur elit molior plaga ratis scisco. Ex mauris minim nulla quis scisco vicis. Commodo ibidem ille metuo nimis plaga ratis suscipere vulpes. Commodo dignissim distineo lucidus praesent quia singularis. Acsi aliquam macto metuo pneum sudo tum. Abico cogo enim pecus praesent turpis. Interdico meus molior vero.\n\nAugue consectetuer decet et lucidus patria praesent saepius saluto singularis. Damnum euismod iusto metuo veniam vicis. Blandit dolore esca singularis uxor. Abbas nutus qui similis validus. Abbas autem facilisi hendrerit odio uxor verto. Abbas dolore esse gilvus minim nisl roto.\n\nFacilisi gilvus loquor natu qui saepius volutpat. Enim magna quis vero virtus. Cui esca gilvus huic incassum nisl praesent ut vicis. Aliquam dolore elit. Cui distineo et laoreet odio pagus patria scisco similis valde. Abdo comis decet plaga suscipit te valde. Abluo ad gemino humo.\n\nPertineo volutpat ymo. Letalis nobis nostrud vel. Caecus eros genitus inhibeo metuo modo nibh nostrud nutus sed. Aliquip bene jumentum olim pala refoveo roto similis.\n\nExerci in natu pala uxor. Cui defui sudo usitas ut. Distineo duis fere molior quadrum ulciscor ullamcorper. Bene eu nostrud virtus. Abluo causa in nimis. Appellatio facilisis importunus in interdico lenis loquor pneum quibus tamen. Abluo macto mauris natu praemitto premo tum venio volutpat. Causa immitto imputo jus nostrud nutus velit.\n\n",
            "format": "plain_text",
            "summary": "Aptent commoveo consectetuer jus nibh plaga sino tincidunt virtus. Diam eligo elit exerci jugis macto voco. Diam mauris pneum sagaciter tincidunt. Camur humo premo. Abdo aliquam conventio enim ideo meus quis valetudo. Capto typicus vicis zelus. Iusto nibh ymo. Dolor laoreet neo qui secundum ulciscor zelus. Esse illum jus.\n\nExerci haero incassum refero. Et occuro qui. Dolor eu exerci gravis inhibeo jugis scisco secundum valde ymo. Decet erat imputo letalis nimis nunc proprius. Iusto olim premo tamen. Consectetuer dignissim erat ex genitus ideo magna nostrud tum. Facilisi illum lucidus nostrud quae velit vero.\n\nAcsi at esca eu illum interdico iriure ratis virtus. Lucidus ludus modo quibus sed. Mauris obruo pala tamen. Abigo abluo aptent causa ea hos luptatum nobis nutus. Acsi aptent at commodo iustum tego zelus. Aliquip ea ille lobortis pertineo quidem utinam voco.\n\nAbbas feugiat populus quae tincidunt valetudo. Laoreet luptatum quibus veniam. Ille illum luptatum utrum. Abico abluo camur dignissim duis eu neo nulla singularis verto. At enim nibh ymo. Nostrud pneum verto. Ad pecus quae. Dolor nibh virtus. Eligo hos melior praesent quidem. Aliquip defui esca gravis neque sagaciter. Ad aliquam et hos iusto obruo occuro quia vero.\n\nAutem eligo loquor nostrud pala rusticus sudo tamen volutpat. Antehabeo defui ideo melior neo validus. Acsi conventio diam eu hos importunus pala refoveo volutpat. Accumsan hos ideo nulla rusticus. Amet appellatio gravis singularis tincidunt vel. Amet imputo persto quidem utinam. Aliquip facilisi in oppeto. Esca inhibeo pertineo sit suscipit. Erat ibidem plaga populus ratis torqueo ullamcorper ymo. Jugis oppeto pala persto refero sagaciter ulciscor.\n\nAliquam amet aptent cogo cui iaceo quibus saluto ullamcorper valde. Blandit dolus macto odio proprius. Consectetuer importunus persto valde vicis. Quia secundum sed typicus. Autem bene esse iustum occuro tego. Camur et ille plaga praesent. Adipiscing blandit et praemitto virtus.\n\nAdipiscing decet haero nisl premo quidem tamen typicus. Amet gemino iustum letalis neque suscipit. Augue damnum iustum modo nobis tum. Aliquam facilisi probo. Consequat enim erat letalis neo nunc qui singularis veniam. Gravis nunc plaga si.\n\nIaceo laoreet mauris tation. Bene occuro pala. Camur elit molior plaga ratis scisco. Ex mauris minim nulla quis scisco vicis. Commodo ibidem ille metuo nimis plaga ratis suscipere vulpes. Commodo dignissim distineo lucidus praesent quia singularis. Acsi aliquam macto metuo pneum sudo tum. Abico cogo enim pecus praesent turpis. Interdico meus molior vero.\n\nAugue consectetuer decet et lucidus patria praesent saepius saluto singularis. Damnum euismod iusto metuo veniam vicis. Blandit dolore esca singularis uxor. Abbas nutus qui similis validus. Abbas autem facilisi hendrerit odio uxor verto. Abbas dolore esse gilvus minim nisl roto.\n\nFacilisi gilvus loquor natu qui saepius volutpat. Enim magna quis vero virtus. Cui esca gilvus huic incassum nisl praesent ut vicis. Aliquam dolore elit. Cui distineo et laoreet odio pagus patria scisco similis valde. Abdo comis decet plaga suscipit te valde. Abluo ad gemino humo.\n\nPertineo volutpat ymo. Letalis nobis nostrud vel. Caecus eros genitus inhibeo metuo modo nibh nostrud nutus sed. Aliquip bene jumentum olim pala refoveo roto similis.\n\nExerci in natu pala uxor. Cui defui sudo usitas ut. Distineo duis fere molior quadrum ulciscor ullamcorper. Bene eu nostrud virtus. Abluo causa in nimis. Appellatio facilisis importunus in interdico lenis loquor pneum quibus tamen. Abluo macto mauris natu praemitto premo tum venio volutpat. Causa immitto imputo jus nostrud nutus velit.\n\n"
        }
    ],
    "field_image": [
        {
            "alt": "Damnum dolor macto pagus suscipere.",
            "title": "Bene blandit cui huic in olim ratis ut.",
            "width": 281,
            "height": 144,
            "target_type": "file",
            "target_uuid": "105072e8-0938-444a-b965-9ea52f6ab5b2"
        }
    ],
    "field_tags": [
        {
            "target_type": "taxonomy_term",
            "target_uuid": "93bea554-82f5-41ab-8a33-969808f0e81f"
        },
        {
            "target_type": "taxonomy_term",
            "target_uuid": "91644d9a-0713-4f97-a29e-e0143736d433"
        },
        {
            "target_type": "taxonomy_term",
            "target_uuid": "8cf3778b-c106-4f3d-a3a4-468cc92ddde8"
        },
        {
            "target_type": "taxonomy_term",
            "target_uuid": "897d8832-6f2f-4426-9838-769fe8663c10"
        },
        {
            "target_type": "taxonomy_term",
            "target_uuid": "91f26b51-dc49-4f1b-86d9-22fc12f5eaf1"
        }
    ]
}