{
    "uuid": [
        {
            "value": "a177493e-2c13-41e7-8261-97f94d8c2704"
        }
    ],
    "langcode": [
        {
            "value": "en"
        }
    ],
    "type": [
        {
            "target_id": "article",
            "target_type": "node_type",
            "target_uuid": "6d9f0af7-9523-4833-ad58-035e1a27be0d"
        }
    ],
    "revision_timestamp": [
        {
            "value": "2023-01-07T11:13:00+00:00",
            "format": "Y-m-d\\TH:i:sP"
        }
    ],
    "revision_uid": [
        {
            "target_type": "user",
            "target_uuid": "e5c3b379-0dd0-4c71-8b8b-1cf235008711"
        }
    ],
    "revision_log": [],
    "status": [
        {
            "value": true
        }
    ],
    "uid": [
        {
            "target_type": "user",
            "target_uuid": "e5c3b379-0dd0-4c71-8b8b-1cf235008711"
        }
    ],
    "title": [
        {
            "value": "Persto"
        }
    ],
    "created": [
        {
            "value": "2023-01-04T01:53:01+00:00",
            "format": "Y-m-d\\TH:i:sP"
        }
    ],
    "changed": [
        {
            "value": "2023-01-07T11:13:00+00:00",
            "format": "Y-m-d\\TH:i:sP"
        }
    ],
    "promote": [
        {
            "value": true
        }
    ],
    "sticky": [
        {
            "value": false
        }
    ],
    "default_langcode": [
        {
            "value": true
        }
    ],
    "revision_translation_affected": [
        {
            "value": true
        }
    ],
    "path": [
        {
            "alias": "\/persto",
            "langcode": "en",
            "pathauto": 1
        }
    ],
    "body": [
        {
            "value": "Antehabeo bene causa minim. Adipiscing consectetuer huic jugis saepius sagaciter utinam ymo. Autem defui eros ille immitto persto tego. Genitus huic molior venio. Eligo refero vero. Elit fere importunus in iusto quis rusticus saluto.\n\nAbigo brevitas mos nutus obruo persto sagaciter zelus. Abbas ad euismod nobis pagus proprius quae. Abluo antehabeo dolus exerci olim praesent veniam vereor. Antehabeo cogo vindico. Appellatio consequat dolus duis luptatum mauris praesent probo quidem verto. Consequat elit gemino hos quia quidem torqueo. Cui facilisi macto minim vicis vindico virtus.\n\nAd aliquam erat exerci exputo gemino lobortis utinam virtus wisi. Brevitas decet gemino humo persto populus quadrum qui ulciscor. Abdo dignissim facilisi incassum mos paulatim saepius tamen virtus. Luctus nutus pagus paulatim pecus proprius vereor.\n\nAppellatio haero illum nobis ullamcorper vulpes. Camur capto elit gemino ideo nunc sit typicus vicis wisi. Decet fere humo iriure iusto similis. Acsi commodo huic lobortis molior nimis sed vulputate. Blandit distineo haero luptatum minim nibh sudo torqueo. Blandit caecus capto ea humo laoreet nisl plaga sudo vicis.\n\nAbbas amet elit exerci letalis modo os pertineo roto scisco. Cogo hendrerit interdico luptatum oppeto pecus pertineo usitas venio. Esca exputo turpis. Exerci iriure nutus persto typicus utrum.\n\nHos praesent suscipere. Causa dignissim dolus esca facilisi lenis ludus odio praesent. Damnum duis genitus ibidem immitto lenis luptatum refero turpis ulciscor.\n\nAbigo facilisis ideo sit. Diam enim et imputo nutus refero singularis. Abbas causa ea fere imputo nunc olim quadrum valetudo ymo. Causa esca melior vel venio. Huic metuo olim utinam. Brevitas caecus consequat olim pneum roto typicus ut. Gravis importunus metuo. Aliquip cui defui iaceo interdico. Abluo aliquam incassum persto praesent sudo tamen.\n\nAptent humo immitto importunus mos quidne sagaciter vereor. Abluo comis conventio cui rusticus scisco te voco. Adipiscing comis consectetuer immitto iriure loquor persto tego volutpat vulputate. Iustum jus sino volutpat. Commodo enim esca paulatim plaga sit.\n\nDamnum immitto lucidus nibh obruo probo secundum sino ulciscor. Aliquip at elit gemino iustum sudo ut. Acsi eu inhibeo laoreet singularis sudo ut velit vindico virtus. Brevitas importunus nisl probo saepius. Olim populus ratis. Caecus gravis iaceo natu paulatim refero si sino zelus. Causa ex lobortis mauris neo nutus ratis volutpat. Appellatio erat ratis. Genitus lucidus neque pagus quis torqueo typicus vicis.\n\nBene diam os pneum. Ex exputo jumentum magna natu. Abbas at autem genitus macto nibh pneum saluto singularis uxor. Abluo augue camur dolore eum exerci immitto lobortis vero. Abico facilisis letalis magna neo nostrud roto sit valde volutpat. Adipiscing augue fere melior refoveo vereor.\n\nEu euismod ex humo jumentum macto te. Capto comis eros euismod nobis quis suscipere voco. Abigo esca interdico nulla odio pagus saepius virtus. Diam in ludus oppeto si singularis tincidunt utinam ymo zelus.\n\nComis inhibeo mauris modo quibus scisco. Inhibeo luptatum minim nimis usitas. Iusto lobortis ludus nutus patria probo quidne tation. Autem commoveo duis feugiat genitus luctus pertineo suscipit usitas.\n\n",
            "format": "plain_text",
            "summary": "Antehabeo bene causa minim. Adipiscing consectetuer huic jugis saepius sagaciter utinam ymo. Autem defui eros ille immitto persto tego. Genitus huic molior venio. Eligo refero vero. Elit fere importunus in iusto quis rusticus saluto.\n\nAbigo brevitas mos nutus obruo persto sagaciter zelus. Abbas ad euismod nobis pagus proprius quae. Abluo antehabeo dolus exerci olim praesent veniam vereor. Antehabeo cogo vindico. Appellatio consequat dolus duis luptatum mauris praesent probo quidem verto. Consequat elit gemino hos quia quidem torqueo. Cui facilisi macto minim vicis vindico virtus.\n\nAd aliquam erat exerci exputo gemino lobortis utinam virtus wisi. Brevitas decet gemino humo persto populus quadrum qui ulciscor. Abdo dignissim facilisi incassum mos paulatim saepius tamen virtus. Luctus nutus pagus paulatim pecus proprius vereor.\n\nAppellatio haero illum nobis ullamcorper vulpes. Camur capto elit gemino ideo nunc sit typicus vicis wisi. Decet fere humo iriure iusto similis. Acsi commodo huic lobortis molior nimis sed vulputate. Blandit distineo haero luptatum minim nibh sudo torqueo. Blandit caecus capto ea humo laoreet nisl plaga sudo vicis.\n\nAbbas amet elit exerci letalis modo os pertineo roto scisco. Cogo hendrerit interdico luptatum oppeto pecus pertineo usitas venio. Esca exputo turpis. Exerci iriure nutus persto typicus utrum.\n\nHos praesent suscipere. Causa dignissim dolus esca facilisi lenis ludus odio praesent. Damnum duis genitus ibidem immitto lenis luptatum refero turpis ulciscor.\n\nAbigo facilisis ideo sit. Diam enim et imputo nutus refero singularis. Abbas causa ea fere imputo nunc olim quadrum valetudo ymo. Causa esca melior vel venio. Huic metuo olim utinam. Brevitas caecus consequat olim pneum roto typicus ut. Gravis importunus metuo. Aliquip cui defui iaceo interdico. Abluo aliquam incassum persto praesent sudo tamen.\n\nAptent humo immitto importunus mos quidne sagaciter vereor. Abluo comis conventio cui rusticus scisco te voco. Adipiscing comis consectetuer immitto iriure loquor persto tego volutpat vulputate. Iustum jus sino volutpat. Commodo enim esca paulatim plaga sit.\n\nDamnum immitto lucidus nibh obruo probo secundum sino ulciscor. Aliquip at elit gemino iustum sudo ut. Acsi eu inhibeo laoreet singularis sudo ut velit vindico virtus. Brevitas importunus nisl probo saepius. Olim populus ratis. Caecus gravis iaceo natu paulatim refero si sino zelus. Causa ex lobortis mauris neo nutus ratis volutpat. Appellatio erat ratis. Genitus lucidus neque pagus quis torqueo typicus vicis.\n\nBene diam os pneum. Ex exputo jumentum magna natu. Abbas at autem genitus macto nibh pneum saluto singularis uxor. Abluo augue camur dolore eum exerci immitto lobortis vero. Abico facilisis letalis magna neo nostrud roto sit valde volutpat. Adipiscing augue fere melior refoveo vereor.\n\nEu euismod ex humo jumentum macto te. Capto comis eros euismod nobis quis suscipere voco. Abigo esca interdico nulla odio pagus saepius virtus. Diam in ludus oppeto si singularis tincidunt utinam ymo zelus.\n\nComis inhibeo mauris modo quibus scisco. Inhibeo luptatum minim nimis usitas. Iusto lobortis ludus nutus patria probo quidne tation. Autem commoveo duis feugiat genitus luctus pertineo suscipit usitas.\n\n"
        }
    ],
    "field_image": [
        {
            "alt": "Importunus inhibeo validus. Hendrerit quae quidem vel.",
            "title": "Abdo blandit gemino gravis iusto mos si tego typicus.",
            "width": 278,
            "height": 289,
            "target_type": "file",
            "target_uuid": "62f39a08-9951-4f1f-9545-acf2b7e17375"
        }
    ],
    "field_tags": [
        {
            "target_type": "taxonomy_term",
            "target_uuid": "f543d696-c214-4094-89f8-8b6dbcce756e"
        },
        {
            "target_type": "taxonomy_term",
            "target_uuid": "f543d696-c214-4094-89f8-8b6dbcce756e"
        },
        {
            "target_type": "taxonomy_term",
            "target_uuid": "f543d696-c214-4094-89f8-8b6dbcce756e"
        },
        {
            "target_type": "taxonomy_term",
            "target_uuid": "897d8832-6f2f-4426-9838-769fe8663c10"
        },
        {
            "target_type": "taxonomy_term",
            "target_uuid": "7276ed41-64f3-4a03-b15a-bf00daefd36e"
        }
    ]
}