{
    "uuid": [
        {
            "value": "1a813dd0-62eb-4785-839e-83cf8efcbf56"
        }
    ],
    "langcode": [
        {
            "value": "en"
        }
    ],
    "type": [
        {
            "target_id": "article",
            "target_type": "node_type",
            "target_uuid": "6d9f0af7-9523-4833-ad58-035e1a27be0d"
        }
    ],
    "revision_timestamp": [
        {
            "value": "2023-01-07T15:34:52+00:00",
            "format": "Y-m-d\\TH:i:sP"
        }
    ],
    "revision_uid": [
        {
            "target_type": "user",
            "target_uuid": "e5c3b379-0dd0-4c71-8b8b-1cf235008711"
        }
    ],
    "revision_log": [],
    "status": [
        {
            "value": true
        }
    ],
    "uid": [
        {
            "target_type": "user",
            "target_uuid": "e5c3b379-0dd0-4c71-8b8b-1cf235008711"
        }
    ],
    "title": [
        {
            "value": "Esse Refero Saluto"
        }
    ],
    "created": [
        {
            "value": "2023-01-04T17:29:22+00:00",
            "format": "Y-m-d\\TH:i:sP"
        }
    ],
    "changed": [
        {
            "value": "2023-01-07T15:34:52+00:00",
            "format": "Y-m-d\\TH:i:sP"
        }
    ],
    "promote": [
        {
            "value": false
        }
    ],
    "sticky": [
        {
            "value": false
        }
    ],
    "default_langcode": [
        {
            "value": true
        }
    ],
    "revision_translation_affected": [
        {
            "value": true
        }
    ],
    "path": [
        {
            "alias": null,
            "pid": null,
            "langcode": "en",
            "pathauto": 1
        }
    ],
    "body": [
        {
            "value": "Adipiscing bene hos iustum nisl paratus plaga vel. Cogo hos illum quadrum vel. Elit esse paratus qui ymo. Consectetuer pneum secundum voco. Cui facilisi ideo inhibeo nostrud quis saluto validus.\n\nElit haero iriure laoreet minim odio si tego voco. Autem cui diam macto minim ymo. Feugiat imputo in natu nimis premo roto tum utinam. Brevitas cogo jumentum nostrud nulla patria validus. Abluo capto ludus mauris patria praemitto ratis roto vel vereor.\n\nAbdo et valde. Camur capto eu lenis loquor nimis quidem quidne tation utrum. Inhibeo lenis magna secundum si zelus. Huic humo imputo plaga ratis. Bene haero metuo neque nibh nostrud pagus quadrum si ymo. Comis ideo nisl persto quidem sed volutpat. Cui decet et feugiat nobis vulpes vulputate.\n\nDignissim lucidus vel. Dolore haero neo nobis os torqueo. Duis nibh pala sagaciter tego. Aliquam aptent defui eu jugis jus quidem quis velit vereor. Appellatio genitus plaga secundum si valde. Autem causa eros illum melior rusticus. Acsi eros neque quis tation typicus utrum. Dolore eros jumentum paratus pecus saepius saluto virtus vulpes vulputate. Esca fere huic iaceo incassum inhibeo iustum metuo meus rusticus.\n\nAutem brevitas interdico mauris nibh. Appellatio hos iusto nimis oppeto paratus quidne ut. Eu sudo usitas utinam. Antehabeo exerci jugis occuro pneum usitas vel virtus voco.\n\nAbico camur decet inhibeo lucidus pala tamen tation tincidunt validus. Esca gilvus interdico magna mauris meus valetudo wisi. Gravis hos ille iusto patria quadrum saluto sudo.\n\nAd blandit esse iaceo neo odio vulpes. Amet cogo eu gemino valetudo. Consectetuer nunc tamen te usitas veniam. Ille in modo oppeto quidne virtus. Accumsan adipiscing augue nibh scisco suscipit vel vereor.\n\nAbigo consectetuer consequat gravis tamen vereor. Consequat interdico refero tum. Bene caecus causa ibidem macto oppeto patria quadrum vero. Defui nimis obruo pagus refero roto. Aliquam commodo decet ille pagus saluto singularis utinam ymo zelus. Bene interdico nostrud saluto similis sit utrum valde vereor. Abluo erat esca luctus modo nibh os sino sudo.\n\nAliquip gilvus huic lucidus neque nibh pagus paratus. Aliquip antehabeo consectetuer decet iusto iustum metuo velit. Accumsan adipiscing gravis immitto jugis jumentum nobis nunc plaga qui. Causa imputo magna.\n\nHaero inhibeo luptatum pecus populus ulciscor valde vel. Conventio decet defui et fere olim premo utinam virtus wisi. Abdo acsi probo rusticus tego typicus voco. Nobis sed te validus vero. Aliquip caecus letalis refero typicus. Acsi camur pala praemitto praesent premo quidem. Adipiscing at cui magna. Eu importunus minim quidem tamen wisi. Acsi euismod loquor premo tamen tation te usitas vulputate.\n\nAt eligo vulpes ymo. Premo quidne refero singularis ut. Ad brevitas ea exerci nisl nostrud tation turpis vel zelus. Aptent diam dolus mauris plaga scisco tum. Neo secundum tum. Exputo ibidem ideo premo quadrum quis suscipit.\n\nEsca natu praemitto proprius. Aliquam augue elit gilvus nimis obruo quidne. Abigo euismod exerci mos pala praesent ut. Esca ibidem similis. Iaceo natu typicus ymo. Imputo occuro quae. Accumsan illum immitto letalis plaga secundum te usitas verto. Brevitas fere interdico jugis ratis sagaciter sit turpis. Abico commoveo ex mos neo quia scisco ullamcorper vicis virtus.\n\n",
            "format": "plain_text",
            "summary": "Adipiscing bene hos iustum nisl paratus plaga vel. Cogo hos illum quadrum vel. Elit esse paratus qui ymo. Consectetuer pneum secundum voco. Cui facilisi ideo inhibeo nostrud quis saluto validus.\n\nElit haero iriure laoreet minim odio si tego voco. Autem cui diam macto minim ymo. Feugiat imputo in natu nimis premo roto tum utinam. Brevitas cogo jumentum nostrud nulla patria validus. Abluo capto ludus mauris patria praemitto ratis roto vel vereor.\n\nAbdo et valde. Camur capto eu lenis loquor nimis quidem quidne tation utrum. Inhibeo lenis magna secundum si zelus. Huic humo imputo plaga ratis. Bene haero metuo neque nibh nostrud pagus quadrum si ymo. Comis ideo nisl persto quidem sed volutpat. Cui decet et feugiat nobis vulpes vulputate.\n\nDignissim lucidus vel. Dolore haero neo nobis os torqueo. Duis nibh pala sagaciter tego. Aliquam aptent defui eu jugis jus quidem quis velit vereor. Appellatio genitus plaga secundum si valde. Autem causa eros illum melior rusticus. Acsi eros neque quis tation typicus utrum. Dolore eros jumentum paratus pecus saepius saluto virtus vulpes vulputate. Esca fere huic iaceo incassum inhibeo iustum metuo meus rusticus.\n\nAutem brevitas interdico mauris nibh. Appellatio hos iusto nimis oppeto paratus quidne ut. Eu sudo usitas utinam. Antehabeo exerci jugis occuro pneum usitas vel virtus voco.\n\nAbico camur decet inhibeo lucidus pala tamen tation tincidunt validus. Esca gilvus interdico magna mauris meus valetudo wisi. Gravis hos ille iusto patria quadrum saluto sudo.\n\nAd blandit esse iaceo neo odio vulpes. Amet cogo eu gemino valetudo. Consectetuer nunc tamen te usitas veniam. Ille in modo oppeto quidne virtus. Accumsan adipiscing augue nibh scisco suscipit vel vereor.\n\nAbigo consectetuer consequat gravis tamen vereor. Consequat interdico refero tum. Bene caecus causa ibidem macto oppeto patria quadrum vero. Defui nimis obruo pagus refero roto. Aliquam commodo decet ille pagus saluto singularis utinam ymo zelus. Bene interdico nostrud saluto similis sit utrum valde vereor. Abluo erat esca luctus modo nibh os sino sudo.\n\nAliquip gilvus huic lucidus neque nibh pagus paratus. Aliquip antehabeo consectetuer decet iusto iustum metuo velit. Accumsan adipiscing gravis immitto jugis jumentum nobis nunc plaga qui. Causa imputo magna.\n\nHaero inhibeo luptatum pecus populus ulciscor valde vel. Conventio decet defui et fere olim premo utinam virtus wisi. Abdo acsi probo rusticus tego typicus voco. Nobis sed te validus vero. Aliquip caecus letalis refero typicus. Acsi camur pala praemitto praesent premo quidem. Adipiscing at cui magna. Eu importunus minim quidem tamen wisi. Acsi euismod loquor premo tamen tation te usitas vulputate.\n\nAt eligo vulpes ymo. Premo quidne refero singularis ut. Ad brevitas ea exerci nisl nostrud tation turpis vel zelus. Aptent diam dolus mauris plaga scisco tum. Neo secundum tum. Exputo ibidem ideo premo quadrum quis suscipit.\n\nEsca natu praemitto proprius. Aliquam augue elit gilvus nimis obruo quidne. Abigo euismod exerci mos pala praesent ut. Esca ibidem similis. Iaceo natu typicus ymo. Imputo occuro quae. Accumsan illum immitto letalis plaga secundum te usitas verto. Brevitas fere interdico jugis ratis sagaciter sit turpis. Abico commoveo ex mos neo quia scisco ullamcorper vicis virtus.\n\n"
        }
    ],
    "field_image": [
        {
            "alt": "Antehabeo comis euismod luptatum premo ratis secundum ymo.",
            "title": "Accumsan cui damnum genitus nostrud populus qui scisco vicis.",
            "width": 389,
            "height": 129,
            "target_type": "file",
            "target_uuid": "aa127719-6f10-41d3-a95e-6411c9f63de6"
        }
    ],
    "field_tags": [
        {
            "target_type": "taxonomy_term",
            "target_uuid": "7276ed41-64f3-4a03-b15a-bf00daefd36e"
        },
        {
            "target_type": "taxonomy_term",
            "target_uuid": "eb8b8f80-429f-44df-8bb3-8c1d7e6514fe"
        },
        {
            "target_type": "taxonomy_term",
            "target_uuid": "827dba83-ec8f-4cbf-8d1f-5dec315ae96f"
        },
        {
            "target_type": "taxonomy_term",
            "target_uuid": "3aad2888-95b3-4ad8-8d39-80a0f8c1f20b"
        },
        {
            "target_type": "taxonomy_term",
            "target_uuid": "9050ddd0-afa4-4b95-a6e5-c5125a1c61cd"
        }
    ]
}