{
    "uuid": [
        {
            "value": "14d36d63-78d4-4926-b9b4-1f3c0bef4a45"
        }
    ],
    "langcode": [
        {
            "value": "en"
        }
    ],
    "type": [
        {
            "target_id": "article",
            "target_type": "node_type",
            "target_uuid": "6d9f0af7-9523-4833-ad58-035e1a27be0d"
        }
    ],
    "revision_timestamp": [
        {
            "value": "2023-01-07T11:14:10+00:00",
            "format": "Y-m-d\\TH:i:sP"
        }
    ],
    "revision_uid": [
        {
            "target_type": "user",
            "target_uuid": "e5c3b379-0dd0-4c71-8b8b-1cf235008711"
        }
    ],
    "revision_log": [],
    "status": [
        {
            "value": true
        }
    ],
    "uid": [
        {
            "target_type": "user",
            "target_uuid": "e5c3b379-0dd0-4c71-8b8b-1cf235008711"
        }
    ],
    "title": [
        {
            "value": "Facilisi Sudo Vulpes"
        }
    ],
    "created": [
        {
            "value": "2023-01-02T05:02:30+00:00",
            "format": "Y-m-d\\TH:i:sP"
        }
    ],
    "changed": [
        {
            "value": "2023-01-07T11:14:10+00:00",
            "format": "Y-m-d\\TH:i:sP"
        }
    ],
    "promote": [
        {
            "value": true
        }
    ],
    "sticky": [
        {
            "value": false
        }
    ],
    "default_langcode": [
        {
            "value": true
        }
    ],
    "revision_translation_affected": [
        {
            "value": true
        }
    ],
    "path": [
        {
            "alias": "\/facilisi-sudo-vulpes",
            "langcode": "en",
            "pathauto": 1
        }
    ],
    "body": [
        {
            "value": "Amet augue ea eum exputo pertineo sed si tum. Augue bene gravis ibidem nobis populus volutpat. Dignissim dolus suscipit. Causa consequat feugiat letalis obruo pagus si te venio. Abigo blandit consequat imputo magna scisco volutpat.\n\nHendrerit quidem secundum torqueo ut. Abigo defui fere hendrerit probo tego wisi. Mauris nobis roto. Eros et luptatum praemitto scisco valde virtus ymo. Bene exerci luptatum mauris nobis premo veniam. Aliquam brevitas dolus eros eu humo lenis lucidus metuo volutpat. Ad adipiscing amet caecus dignissim distineo gilvus jugis praemitto praesent. Elit esca ille nibh paratus usitas utinam venio.\n\nDolor gilvus ille iriure lobortis sed. Elit esca hos nobis qui sagaciter typicus verto. Acsi iriure macto natu persto plaga ulciscor. Accumsan iusto pneum praemitto tego vel. Amet diam eligo imputo mos refero te. Abbas consequat feugiat humo neque veniam. Abluo autem consectetuer exerci macto mos neque ratis secundum valde. Accumsan eros luptatum natu ullamcorper virtus. Dolus laoreet luctus modo nulla probo saluto tation torqueo ullamcorper.\n\nAccumsan capto ea esca et probo vel voco. Ibidem nunc premo secundum. Cui dolore fere persto. Accumsan antehabeo comis decet eligo melior mos oppeto quidne tation. Eu incassum jugis quae saluto turpis velit. Iaceo metuo patria quadrum similis tation tum.\n\nCommoveo distineo exputo interdico neo probo. Comis exputo nutus obruo te vereor. Dolus gilvus inhibeo meus nibh nutus praemitto vicis. Abico eu ex ibidem illum nibh persto scisco vindico. Cogo cui euismod mauris nibh ullamcorper. Augue dignissim eu ibidem mauris plaga quidne similis.\n\nDistineo iusto suscipere ymo. Gemino genitus lenis sino suscipit virtus. Bene conventio ille pagus roto valde. Distineo esca modo nutus plaga turpis. Acsi commoveo decet enim esca os ratis uxor vero. Ex magna pertineo quis. Consequat eu gilvus hos interdico metuo nobis. Diam euismod lucidus luctus metuo probo vulpes.\n\nConventio luptatum meus refoveo. Autem eros fere hos ille melior veniam. Commodo conventio eligo genitus haero ideo iustum persto ymo. Ille laoreet metuo. Commoveo dignissim inhibeo mos pala te vero. Eum nobis nutus quidne scisco sit. Aptent bene elit gravis jus magna zelus.\n\nAppellatio esse letalis lobortis modo nibh nobis scisco si. Blandit defui ea exerci iusto lobortis patria. Aliquip feugiat gravis mauris probo refero volutpat. Cogo commodo defui dolus esse iaceo nibh suscipit. Duis laoreet nobis veniam. Comis distineo dolore ea exerci magna roto tincidunt venio wisi. Commodo iaceo interdico iustum jumentum occuro persto. Abbas caecus dignissim exputo iriure jus te.\n\nCui elit lenis nostrud singularis. Comis cui damnum melior nibh odio utinam. Camur jugis lucidus magna paulatim proprius ratis saepius. Accumsan antehabeo damnum dolore elit facilisis fere nunc odio oppeto. Dolor duis imputo laoreet minim molior nibh odio tincidunt vero. Camur cogo ex gilvus haero occuro scisco si usitas. Decet defui jus ludus sagaciter utrum.\n\nQuadrum valetudo vereor ymo. Eros nutus vereor. Accumsan caecus iaceo iustum jumentum obruo pagus paulatim usitas vulpes. Ibidem ludus singularis utrum volutpat ymo. Quidne sino sit uxor. Accumsan adipiscing incassum premo sudo te tego usitas.\n\nConventio quibus typicus. Facilisis huic immitto imputo luptatum typicus. Dignissim loquor meus premo te vulputate. Dolus imputo macto magna obruo quis ulciscor. Acsi lucidus melior metuo quibus validus velit vereor verto. Abdo antehabeo augue capto diam esse qui. Abdo accumsan cui pagus tincidunt ullamcorper valde. Caecus eu suscipit utinam volutpat. Ad esse ibidem molior pala sagaciter sudo virtus.\n\nAccumsan ideo immitto persto. Ille qui quia singularis sino turpis valetudo vereor ymo. Defui eligo erat mos uxor. Ad molior paulatim. Ad dignissim exerci magna paulatim scisco secundum ullamcorper venio. Damnum duis ludus nisl obruo ratis sino ulciscor vel vulputate. Augue camur comis commodo commoveo consectetuer elit humo. Accumsan caecus dolor jumentum tamen. Accumsan ex imputo os persto.\n\n",
            "format": "plain_text",
            "summary": "Amet augue ea eum exputo pertineo sed si tum. Augue bene gravis ibidem nobis populus volutpat. Dignissim dolus suscipit. Causa consequat feugiat letalis obruo pagus si te venio. Abigo blandit consequat imputo magna scisco volutpat.\n\nHendrerit quidem secundum torqueo ut. Abigo defui fere hendrerit probo tego wisi. Mauris nobis roto. Eros et luptatum praemitto scisco valde virtus ymo. Bene exerci luptatum mauris nobis premo veniam. Aliquam brevitas dolus eros eu humo lenis lucidus metuo volutpat. Ad adipiscing amet caecus dignissim distineo gilvus jugis praemitto praesent. Elit esca ille nibh paratus usitas utinam venio.\n\nDolor gilvus ille iriure lobortis sed. Elit esca hos nobis qui sagaciter typicus verto. Acsi iriure macto natu persto plaga ulciscor. Accumsan iusto pneum praemitto tego vel. Amet diam eligo imputo mos refero te. Abbas consequat feugiat humo neque veniam. Abluo autem consectetuer exerci macto mos neque ratis secundum valde. Accumsan eros luptatum natu ullamcorper virtus. Dolus laoreet luctus modo nulla probo saluto tation torqueo ullamcorper.\n\nAccumsan capto ea esca et probo vel voco. Ibidem nunc premo secundum. Cui dolore fere persto. Accumsan antehabeo comis decet eligo melior mos oppeto quidne tation. Eu incassum jugis quae saluto turpis velit. Iaceo metuo patria quadrum similis tation tum.\n\nCommoveo distineo exputo interdico neo probo. Comis exputo nutus obruo te vereor. Dolus gilvus inhibeo meus nibh nutus praemitto vicis. Abico eu ex ibidem illum nibh persto scisco vindico. Cogo cui euismod mauris nibh ullamcorper. Augue dignissim eu ibidem mauris plaga quidne similis.\n\nDistineo iusto suscipere ymo. Gemino genitus lenis sino suscipit virtus. Bene conventio ille pagus roto valde. Distineo esca modo nutus plaga turpis. Acsi commoveo decet enim esca os ratis uxor vero. Ex magna pertineo quis. Consequat eu gilvus hos interdico metuo nobis. Diam euismod lucidus luctus metuo probo vulpes.\n\nConventio luptatum meus refoveo. Autem eros fere hos ille melior veniam. Commodo conventio eligo genitus haero ideo iustum persto ymo. Ille laoreet metuo. Commoveo dignissim inhibeo mos pala te vero. Eum nobis nutus quidne scisco sit. Aptent bene elit gravis jus magna zelus.\n\nAppellatio esse letalis lobortis modo nibh nobis scisco si. Blandit defui ea exerci iusto lobortis patria. Aliquip feugiat gravis mauris probo refero volutpat. Cogo commodo defui dolus esse iaceo nibh suscipit. Duis laoreet nobis veniam. Comis distineo dolore ea exerci magna roto tincidunt venio wisi. Commodo iaceo interdico iustum jumentum occuro persto. Abbas caecus dignissim exputo iriure jus te.\n\nCui elit lenis nostrud singularis. Comis cui damnum melior nibh odio utinam. Camur jugis lucidus magna paulatim proprius ratis saepius. Accumsan antehabeo damnum dolore elit facilisis fere nunc odio oppeto. Dolor duis imputo laoreet minim molior nibh odio tincidunt vero. Camur cogo ex gilvus haero occuro scisco si usitas. Decet defui jus ludus sagaciter utrum.\n\nQuadrum valetudo vereor ymo. Eros nutus vereor. Accumsan caecus iaceo iustum jumentum obruo pagus paulatim usitas vulpes. Ibidem ludus singularis utrum volutpat ymo. Quidne sino sit uxor. Accumsan adipiscing incassum premo sudo te tego usitas.\n\nConventio quibus typicus. Facilisis huic immitto imputo luptatum typicus. Dignissim loquor meus premo te vulputate. Dolus imputo macto magna obruo quis ulciscor. Acsi lucidus melior metuo quibus validus velit vereor verto. Abdo antehabeo augue capto diam esse qui. Abdo accumsan cui pagus tincidunt ullamcorper valde. Caecus eu suscipit utinam volutpat. Ad esse ibidem molior pala sagaciter sudo virtus.\n\nAccumsan ideo immitto persto. Ille qui quia singularis sino turpis valetudo vereor ymo. Defui eligo erat mos uxor. Ad molior paulatim. Ad dignissim exerci magna paulatim scisco secundum ullamcorper venio. Damnum duis ludus nisl obruo ratis sino ulciscor vel vulputate. Augue camur comis commodo commoveo consectetuer elit humo. Accumsan caecus dolor jumentum tamen. Accumsan ex imputo os persto.\n\n"
        }
    ],
    "field_image": [
        {
            "alt": "Magna occuro turpis typicus.",
            "title": "Aptent eu genitus gravis haero iaceo ludus nostrud sino vel.",
            "width": 360,
            "height": 491,
            "target_type": "file",
            "target_uuid": "f8fa2925-8b0c-4cb8-a0c0-ce3848d0157f"
        }
    ],
    "field_tags": [
        {
            "target_type": "taxonomy_term",
            "target_uuid": "2735692b-ca41-45fc-bafe-27b62175b130"
        },
        {
            "target_type": "taxonomy_term",
            "target_uuid": "2ac26517-f9dc-4aa8-a7f3-b2cf3c46b973"
        },
        {
            "target_type": "taxonomy_term",
            "target_uuid": "39f767d9-2c7a-4f96-9dec-7a89a7d74375"
        },
        {
            "target_type": "taxonomy_term",
            "target_uuid": "d3cf6488-d853-404a-948a-2833c0a648c6"
        },
        {
            "target_type": "taxonomy_term",
            "target_uuid": "94ea31fa-b5e4-41b0-be08-12ed918af715"
        }
    ]
}